[
  {
    "caseNumber(Count)": "2023-020596-CA-01",
    "caseType": "FORECLOSURE",
    "finalJudgmentAmount": "$352,956.17",
    "parcelID": "01-3126-042-0050",
    "assessedValue": "$55,900.00",
    "propertyAppraiserLegalDescription": "THE EAST 30 FEET OF LOT 7 AND THE WEST 20 FEET OF LOT 8, BLOCK 1, ALLAPATTAH PARK, ACCORDING TO THE MAP OR PLAT THEREOF AS RECORDED IN PLAT BOOK 6, PAGE 64 OF THE PUBLIC RECORDS OF DADE COUNTY, FLORIDA. PROPERTY ADDRESS: 1521 NW 31ST ST, MIAMI, FL 33142",
    "partyDetails": [
      {
        "DEFENDANT": "UNITED STATES OF AMERICA ON BEHALF OF THE SECR"
      },
      {
        "DEFENDANT": "GULLATT, ESTER M"
      },
      {
        "DEFENDANT AKA": "FORSYTHE (ESTATE OF) (DECEASED, ESTER"
      },
      {
        "DEFENDANT-ATTORNEY": "Lauck, Lisa Marie"
      },
      {
        "PLAINTIFF": "BANK OF NEW YORK MELLON TRUST COMPANY NA AS TRU"
      },
      {
        "PLAINTIFF-ATTORNEY": "Meisels, Jonathan Ian"
      }
    ],
    "url": "https://www.miamidade.gov/Apps/PA/PApublicServiceProxy/PaServicesProxy.ashx?Operation=GetPropertySearchByFolio&clientAppName=PropertySearch&folioNumber=0131260420050",
    "bathrooms": 1,
    "bedrooms": 2,
    "floors": 1,
    "municipality": "Miami",
    "lotSize": 6900,
    "primaryLandUse": "0101RESIDENTIAL - SINGLE FAMILY : 1 UNIT",
    "livingArea": 1123,
    "yearBuilt": "Multiple (See Building Info.)",
    "primaryZone": "DUPLEXES - GENERAL",
    "subdivision": "ALLAPATTAH PARK",
    "neighborhood": "SANTA CLARA",
    "buildingArea": 1172,
    "description": "RESIDENTIAL - SINGLE FAMILY : 1 UNIT",
    "units": 1,
    "siteAddress": "1521 NW 31 ST, Miami, FL 33142-6140",
    "totalValue": 353879,
    "qualifiedOwner": [],
    "owners": [
      {
        "name": "ESTER GULLATT",
        "percentage": 0,
        "married": "No",
        "description": ""
      }
    ],
    "taxCollectorDebt": 0,
    "violations": [],
    "legalDocuments": [
      [],
      [],
      [
        {
          "url": "https://onlineservices.miamidadeclerk.gov/officialrecords/CFNDetailsPDF.aspx?QS=5p8%2fNlBjKYBnmQuTdNWFp8GIPWDODZs%2fMDhnq1sxLV9Wdl2ypMSaWA%3d%3d",
          "type": "LIS",
          "firstParty": "GULLATT ESTER M (R)",
          "secondParty": "BANK OF NEW YORK MELLON TRUST COMPANY NA AS TRU",
          "date": "8/3/2023",
          "fileNumber": "2023 R 539284"
        },
        {
          "url": "https://onlineservices.miamidadeclerk.gov/officialrecords/CFNDetailsPDF.aspx?QS=5p8%2fNlBjKYA4k247K9v%2bZyhSzlUCBXMt6lrs8wDVdsZoRdeSUMf8dw%3d%3d",
          "type": "DCP",
          "firstParty": "GULLATT ESTER M (R)",
          "secondParty": "BANK OF NEW YORK MELLON TRUST COMPANY NA AS TRU",
          "date": "5/14/2024",
          "fileNumber": "2024 R 368089"
        }
      ],
      [],
      [],
      [],
      [
        {
          "url": "https://onlineservices.miamidadeclerk.gov/officialrecords/CFNDetailsPDF.aspx?QS=5p8%2fNlBjKYBarc%2fJA16mTsQXudBIaozyPsRJtgRvgEAwJrgIkMeQgw%3d%3d",
          "type": "DCP",
          "firstParty": "MEISELS JONATHAN IAN (R)",
          "secondParty": "NATIONSTAR MORTGAGE LLC",
          "date": "5/9/2017",
          "fileNumber": "2017 R 260816"
        },
        {
          "url": "https://onlineservices.miamidadeclerk.gov/officialrecords/CFNDetailsPDF.aspx?QS=5p8%2fNlBjKYBarc%2fJA16mThC3KBY0ar8wz%2blRPcMczUM%2bDDKBxsTN%2bQ%3d%3d",
          "type": "LIS",
          "firstParty": "MEISELS JONATHAN IAN (R)",
          "secondParty": "OVIEDO ALFONSO E",
          "date": "9/18/2017",
          "fileNumber": "2017 R 519322"
        },
        {
          "url": "https://onlineservices.miamidadeclerk.gov/officialrecords/CFNDetailsPDF.aspx?QS=5p8%2fNlBjKYBarc%2fJA16mTvd47z2PLCcWQWnwhND2N83k4udXbWEV%2bg%3d%3d",
          "type": "LIS",
          "firstParty": "MEISELS JONATHAN IAN (R)",
          "secondParty": "OVIEDO ALFONSO E",
          "date": "9/21/2017",
          "fileNumber": "2017 R 529767"
        },
        {
          "url": "https://onlineservices.miamidadeclerk.gov/officialrecords/CFNDetailsPDF.aspx?QS=5p8%2fNlBjKYBarc%2fJA16mTvPR57sYV%2fU5jSNVS2mZKIGJFMLyptzKxw%3d%3d",
          "type": "DCP",
          "firstParty": "MEISELS JONATHAN IAN (R)",
          "secondParty": "NATIONSTAR MORTGAGE LLC",
          "date": "11/2/2017",
          "fileNumber": "2017 R 619482"
        },
        {
          "url": "https://onlineservices.miamidadeclerk.gov/officialrecords/CFNDetailsPDF.aspx?QS=5p8%2fNlBjKYBUVFWUfUcSy3l%2fNKogNRhPT61Q83GGyVFWfdAdWZvGNg%3d%3d",
          "type": "DCP",
          "firstParty": "MEISELS JONATHAN IAN (R)",
          "secondParty": "OVIEDO ALFONSO E",
          "date": "5/16/2018",
          "fileNumber": "2018 R 289884"
        },
        {
          "url": "https://onlineservices.miamidadeclerk.gov/officialrecords/CFNDetailsPDF.aspx?QS=5p8%2fNlBjKYBUVFWUfUcSyw1QGQdZTpNxhaO%2bSA9hgAidhnz9tGFRDg%3d%3d",
          "type": "DCP",
          "firstParty": "MEISELS JONATHAN IAN (R)",
          "secondParty": "OVIEDO ALFONSO E",
          "date": "6/15/2018",
          "fileNumber": "2018 R 355080"
        },
        {
          "url": "https://onlineservices.miamidadeclerk.gov/officialrecords/CFNDetailsPDF.aspx?QS=5p8%2fNlBjKYBUVFWUfUcSy%2fZQ6jVrSiYCsTL%2fn3qv5Mnf3NZB9UfGmQ%3d%3d",
          "type": "LIS",
          "firstParty": "MEISELS JONATHAN IAN (D)",
          "secondParty": "UNKNOWN SPOUSE OF JOSE M MIRANDA",
          "date": "10/3/2018",
          "fileNumber": "2018 R 603768"
        },
        {
          "url": "https://onlineservices.miamidadeclerk.gov/officialrecords/CFNDetailsPDF.aspx?QS=5p8%2fNlBjKYBUVFWUfUcSyzgas%2b0x0gnwDUjXPsQ9ujCBCXsDOzfXnA%3d%3d",
          "type": "DCP",
          "firstParty": "MEISELS JONATHAN IAN (R)",
          "secondParty": "NATIONSTAR MORTGAGE LLC",
          "date": "12/14/2018",
          "fileNumber": "2018 R 753992"
        },
        {
          "url": "https://onlineservices.miamidadeclerk.gov/officialrecords/CFNDetailsPDF.aspx?QS=5p8%2fNlBjKYC3mpaYv1a%2bncVsQbfW2jQ94zgunzS%2bCLWRcZJnfLMxGQ%3d%3d",
          "type": "DCP",
          "firstParty": "MEISELS JONATHAN IAN (D)",
          "secondParty": "UNKNOWN SPOUSE OF JOSE M MIRANDA",
          "date": "5/23/2019",
          "fileNumber": "2019 R 321503"
        },
        {
          "url": "https://onlineservices.miamidadeclerk.gov/officialrecords/CFNDetailsPDF.aspx?QS=5p8%2fNlBjKYC3mpaYv1a%2bnTxbz%2bMgvrIui2GcQgrKFiTPXRG123nL8A%3d%3d",
          "type": "DCP",
          "firstParty": "MEISELS JONATHAN IAN (D)",
          "secondParty": "UNKNOWN SPOUSE OF JOSE M MIRANDA",
          "date": "6/4/2019",
          "fileNumber": "2019 R 345503"
        },
        {
          "url": "https://onlineservices.miamidadeclerk.gov/officialrecords/CFNDetailsPDF.aspx?QS=5p8%2fNlBjKYC3mpaYv1a%2bne%2bFB%2fhyYCnkWw1klNrF5SiooE983SkYnQ%3d%3d",
          "type": "DCP",
          "firstParty": "MEISELS JONATHAN IAN (R)",
          "secondParty": "OVIEDO ALFONSO E",
          "date": "9/11/2019",
          "fileNumber": "2019 R 568687"
        }
      ]
    ]
  },
  {
    "caseNumber(Count)": "2023-020596-CA-01",
    "caseType": "FORECLOSURE",
    "finalJudgmentAmount": "$352,956.17",
    "parcelID": "01-3126-042-0050",
    "assessedValue": "$55,900.00",
    "propertyAppraiserLegalDescription": "THE EAST 30 FEET OF LOT 7 AND THE WEST 20 FEET OF LOT 8, BLOCK 1, ALLAPATTAH PARK, ACCORDING TO THE MAP OR PLAT THEREOF AS RECORDED IN PLAT BOOK 6, PAGE 64 OF THE PUBLIC RECORDS OF DADE COUNTY, FLORIDA. PROPERTY ADDRESS: 1521 NW 31ST ST, MIAMI, FL 33142",
    "partyDetails": [
      {
        "DEFENDANT": "UNITED STATES OF AMERICA ON BEHALF OF THE SECR"
      },
      {
        "DEFENDANT": "GULLATT, ESTER M"
      },
      {
        "DEFENDANT AKA": "FORSYTHE (ESTATE OF) (DECEASED, ESTER"
      },
      {
        "DEFENDANT-ATTORNEY": "Lauck, Lisa Marie"
      },
      {
        "PLAINTIFF": "BANK OF NEW YORK MELLON TRUST COMPANY NA AS TRU"
      },
      {
        "PLAINTIFF-ATTORNEY": "Meisels, Jonathan Ian"
      }
    ],
    "url": "https://www.miamidade.gov/Apps/PA/PApublicServiceProxy/PaServicesProxy.ashx?Operation=GetPropertySearchByFolio&clientAppName=PropertySearch&folioNumber=0131260420050",
    "bathrooms": 1,
    "bedrooms": 2,
    "floors": 1,
    "municipality": "Miami",
    "lotSize": 6900,
    "primaryLandUse": "0101RESIDENTIAL - SINGLE FAMILY : 1 UNIT",
    "livingArea": 1123,
    "yearBuilt": "Multiple (See Building Info.)",
    "primaryZone": "DUPLEXES - GENERAL",
    "subdivision": "ALLAPATTAH PARK",
    "neighborhood": "SANTA CLARA",
    "buildingArea": 1172,
    "description": "RESIDENTIAL - SINGLE FAMILY : 1 UNIT",
    "units": 1,
    "siteAddress": "1521 NW 31 ST, Miami, FL 33142-6140",
    "totalValue": 353879,
    "qualifiedOwner": [],
    "owners": [
      {
        "name": "ESTER GULLATT",
        "percentage": 0,
        "married": "No",
        "description": ""
      }
    ],
    "taxCollectorDebt": 0,
    "violations": [
      {
        "amount": "$260.00",
        "status": " OPEN ",
        "description": "UNAUTHORIZED TAMPERING WITH UTILITY FIXTURES AT A SINGLE FAMILY RESIDENTIAL PROPERTY",
        "codeSection": "32-121"
      }
    ],
    "legalDocuments": [
      [],
      [],
      [
        {
          "url": "https://onlineservices.miamidadeclerk.gov/officialrecords/CFNDetailsPDF.aspx?QS=5p8%2fNlBjKYBnmQuTdNWFp8GIPWDODZs%2fMDhnq1sxLV9Wdl2ypMSaWA%3d%3d",
          "type": "LIS",
          "firstParty": "GULLATT ESTER M (R)",
          "secondParty": "BANK OF NEW YORK MELLON TRUST COMPANY NA AS TRU",
          "date": "8/3/2023",
          "fileNumber": "2023 R 539284"
        },
        {
          "url": "https://onlineservices.miamidadeclerk.gov/officialrecords/CFNDetailsPDF.aspx?QS=5p8%2fNlBjKYA4k247K9v%2bZyhSzlUCBXMt6lrs8wDVdsZoRdeSUMf8dw%3d%3d",
          "type": "DCP",
          "firstParty": "GULLATT ESTER M (R)",
          "secondParty": "BANK OF NEW YORK MELLON TRUST COMPANY NA AS TRU",
          "date": "5/14/2024",
          "fileNumber": "2024 R 368089"
        }
      ],
      [],
      [],
      [],
      [
        {
          "url": "https://onlineservices.miamidadeclerk.gov/officialrecords/CFNDetailsPDF.aspx?QS=5p8%2fNlBjKYBarc%2fJA16mTsQXudBIaozyPsRJtgRvgEAwJrgIkMeQgw%3d%3d",
          "type": "DCP",
          "firstParty": "MEISELS JONATHAN IAN (R)",
          "secondParty": "NATIONSTAR MORTGAGE LLC",
          "date": "5/9/2017",
          "fileNumber": "2017 R 260816"
        },
        {
          "url": "https://onlineservices.miamidadeclerk.gov/officialrecords/CFNDetailsPDF.aspx?QS=5p8%2fNlBjKYBarc%2fJA16mThC3KBY0ar8wz%2blRPcMczUM%2bDDKBxsTN%2bQ%3d%3d",
          "type": "LIS",
          "firstParty": "MEISELS JONATHAN IAN (R)",
          "secondParty": "OVIEDO ALFONSO E",
          "date": "9/18/2017",
          "fileNumber": "2017 R 519322"
        },
        {
          "url": "https://onlineservices.miamidadeclerk.gov/officialrecords/CFNDetailsPDF.aspx?QS=5p8%2fNlBjKYBarc%2fJA16mTvd47z2PLCcWQWnwhND2N83k4udXbWEV%2bg%3d%3d",
          "type": "LIS",
          "firstParty": "MEISELS JONATHAN IAN (R)",
          "secondParty": "OVIEDO ALFONSO E",
          "date": "9/21/2017",
          "fileNumber": "2017 R 529767"
        },
        {
          "url": "https://onlineservices.miamidadeclerk.gov/officialrecords/CFNDetailsPDF.aspx?QS=5p8%2fNlBjKYBarc%2fJA16mTvPR57sYV%2fU5jSNVS2mZKIGJFMLyptzKxw%3d%3d",
          "type": "DCP",
          "firstParty": "MEISELS JONATHAN IAN (R)",
          "secondParty": "NATIONSTAR MORTGAGE LLC",
          "date": "11/2/2017",
          "fileNumber": "2017 R 619482"
        },
        {
          "url": "https://onlineservices.miamidadeclerk.gov/officialrecords/CFNDetailsPDF.aspx?QS=5p8%2fNlBjKYBUVFWUfUcSy3l%2fNKogNRhPT61Q83GGyVFWfdAdWZvGNg%3d%3d",
          "type": "DCP",
          "firstParty": "MEISELS JONATHAN IAN (R)",
          "secondParty": "OVIEDO ALFONSO E",
          "date": "5/16/2018",
          "fileNumber": "2018 R 289884"
        },
        {
          "url": "https://onlineservices.miamidadeclerk.gov/officialrecords/CFNDetailsPDF.aspx?QS=5p8%2fNlBjKYBUVFWUfUcSyw1QGQdZTpNxhaO%2bSA9hgAidhnz9tGFRDg%3d%3d",
          "type": "DCP",
          "firstParty": "MEISELS JONATHAN IAN (R)",
          "secondParty": "OVIEDO ALFONSO E",
          "date": "6/15/2018",
          "fileNumber": "2018 R 355080"
        },
        {
          "url": "https://onlineservices.miamidadeclerk.gov/officialrecords/CFNDetailsPDF.aspx?QS=5p8%2fNlBjKYBUVFWUfUcSy%2fZQ6jVrSiYCsTL%2fn3qv5Mnf3NZB9UfGmQ%3d%3d",
          "type": "LIS",
          "firstParty": "MEISELS JONATHAN IAN (D)",
          "secondParty": "UNKNOWN SPOUSE OF JOSE M MIRANDA",
          "date": "10/3/2018",
          "fileNumber": "2018 R 603768"
        },
        {
          "url": "https://onlineservices.miamidadeclerk.gov/officialrecords/CFNDetailsPDF.aspx?QS=5p8%2fNlBjKYBUVFWUfUcSyzgas%2b0x0gnwDUjXPsQ9ujCBCXsDOzfXnA%3d%3d",
          "type": "DCP",
          "firstParty": "MEISELS JONATHAN IAN (R)",
          "secondParty": "NATIONSTAR MORTGAGE LLC",
          "date": "12/14/2018",
          "fileNumber": "2018 R 753992"
        },
        {
          "url": "https://onlineservices.miamidadeclerk.gov/officialrecords/CFNDetailsPDF.aspx?QS=5p8%2fNlBjKYC3mpaYv1a%2bncVsQbfW2jQ94zgunzS%2bCLWRcZJnfLMxGQ%3d%3d",
          "type": "DCP",
          "firstParty": "MEISELS JONATHAN IAN (D)",
          "secondParty": "UNKNOWN SPOUSE OF JOSE M MIRANDA",
          "date": "5/23/2019",
          "fileNumber": "2019 R 321503"
        },
        {
          "url": "https://onlineservices.miamidadeclerk.gov/officialrecords/CFNDetailsPDF.aspx?QS=5p8%2fNlBjKYC3mpaYv1a%2bnTxbz%2bMgvrIui2GcQgrKFiTPXRG123nL8A%3d%3d",
          "type": "DCP",
          "firstParty": "MEISELS JONATHAN IAN (D)",
          "secondParty": "UNKNOWN SPOUSE OF JOSE M MIRANDA",
          "date": "6/4/2019",
          "fileNumber": "2019 R 345503"
        },
        {
          "url": "https://onlineservices.miamidadeclerk.gov/officialrecords/CFNDetailsPDF.aspx?QS=5p8%2fNlBjKYC3mpaYv1a%2bne%2bFB%2fhyYCnkWw1klNrF5SiooE983SkYnQ%3d%3d",
          "type": "DCP",
          "firstParty": "MEISELS JONATHAN IAN (R)",
          "secondParty": "OVIEDO ALFONSO E",
          "date": "9/11/2019",
          "fileNumber": "2019 R 568687"
        }
      ]
    ]
  }
]